vibetest/__init__.py
vibetest/agents.py
vibetest/mcp_server.py
mseep_vibetest-0.1.1.dist-info/METADATA
mseep_vibetest-0.1.1.dist-info/WHEEL
mseep_vibetest-0.1.1.dist-info/entry_points.txt
mseep_vibetest-0.1.1.dist-info/top_level.txt
mseep_vibetest-0.1.1.dist-info/RECORD
